subbucalculator/__init__.py
subbucalculator-0.1.dist-info/LICENSE.txt
subbucalculator-0.1.dist-info/METADATA
subbucalculator-0.1.dist-info/WHEEL
subbucalculator-0.1.dist-info/top_level.txt
subbucalculator-0.1.dist-info/RECORD
