Metadata-Version: 2.1
Name: subbucalculator
Version: 0.1
Summary: Basic Calculator
Author: Subramani K P
Author-email: subbukp690@gmail.com
Classifier: Programming Language :: Python :: 3
Classifier: License :: OSI Approved :: MIT License
Classifier: Operating System :: OS Independent
License-File: LICENSE.txt
